<entry xml:lang="en">
<form type="lemma">
<orth>
scour
</orth>
<form type="variant">
<pron>
/sk*a*U*@/
</pron>
</form>
<form type="inflected">
scours, scouring, scoured.
</form>
</form>
<sense>
<gramGrp>
<pos>
VB 
<seg>
with 
</seg>
OBJ
</pos>
</gramGrp>
<def xml:lang="sl">
<seg type="lemma">
To scour a place for something 
</seg>
pomeni temeljito pregledati neki kraj, ker nekaj i&scaron;&ccaron;emo. 
</def>
<cit type="translationEquivalent">
<quote>
prebrskati, preiskati
</quote>
</cit>
<seg type="example">
<quote>
Traders were scouring the villages for family treasures.
</quote>
</seg>
</sense>
</entry>
