<entry xml:lang="en">
<form type="lemma">
<orth>
<TOKEN sid="p91_s100292" id="p91_w864" font-name="ssunivers" serif="yes" fixed-width="yes" bold="yes" italic="no" font-size="9" font-color="#000000" rotation="0" angle="0" x="255.14" y="372.052" base="378.46" width="17.1" height="8.514">butt</TOKEN>
</orth>
<form type="variant">
<pron>
<TOKEN sid="p91_s100293" id="p91_w865" font-name="ssexcelsior" serif="yes" bold="no" italic="no" font-size="7.25" font-color="#000000" rotation="0" angle="0" x="274.13" y="373.298" base="378.46" width="19.0016" height="6.844">/bØt/,</TOKEN>
</pron>
</form>
<form type="inflected">
<TOKEN sid="p91_s100294" id="p91_w866" font-name="ssunivers" bold="no" italic="no" font-size="7.5" font-color="#000000" rotation="0" angle="0" x="295.03" y="373.12" base="378.46" width="17.9888" height="7.08">butts,</TOKEN>
<TOKEN sid="p91_s100295" id="p91_w867" font-name="ssunivers" bold="no" italic="no" font-size="7.5" font-color="#000000" rotation="0" angle="0" x="314.793" y="373.12" base="378.46" width="24.7361" height="7.08">butting,</TOKEN>
<TOKEN sid="p91_s100296" id="p91_w868" font-name="ssunivers" bold="no" italic="no" font-size="7.5" font-color="#000000" rotation="0" angle="0" x="341.303" y="373.12" base="378.46" width="22.4897" height="7.08">butted.</TOKEN>
</form>
</form>
<sense n="1">
<gramGrp>
<pos>
<TOKEN sid="p91_s100298" id="p91_w870" font-name="ssexcelsior" serif="yes" bold="no" italic="no" font-size="5.5" font-color="#000000" rotation="0" angle="0" x="372.25" y="374.544" base="378.46" width="18.9714" height="5.192">COUNT</TOKEN>
<TOKEN sid="p91_s100299" id="p91_w871" font-name="ssexcelsior" serif="yes" bold="no" italic="no" font-size="5.5" font-color="#000000" rotation="0" angle="0" x="392.527" y="374.544" base="378.46" width="4.12335" height="5.192">N</TOKEN>
</pos>
</gramGrp>
<def xml:lang="sl">
<seg type="lemma">
<TOKEN sid="p91_s100300" id="p91_w872" font-name="ssexcelsior" bold="yes" italic="no" font-size="8" font-color="#000000" rotation="0" angle="0" x="398.54" y="372.764" base="378.46" width="12.7987" height="7.552">The</TOKEN>
<TOKEN sid="p91_s100301" id="p91_w873" font-name="ssexcelsior" bold="yes" italic="no" font-size="8" font-color="#000000" rotation="0" angle="0" x="413.228" y="372.764" base="378.46" width="14.3957" height="7.552">butt</TOKEN>
<TOKEN sid="p91_s100302" id="p91_w874" font-name="ssexcelsior" bold="yes" italic="no" font-size="8" font-color="#000000" rotation="0" angle="0" x="429.513" y="372.764" base="378.46" width="6.80256" height="7.552">of</TOKEN>
<TOKEN sid="p91_s100303" id="p91_w875" font-name="ssexcelsior" bold="yes" italic="no" font-size="8" font-color="#000000" rotation="0" angle="0" x="438.205" y="372.764" base="378.46" width="4.0032" height="7.552">a</TOKEN>
<TOKEN sid="p91_s100304" id="p91_w876" font-name="ssexcelsior" bold="yes" italic="no" font-size="8" font-color="#000000" rotation="0" angle="0" x="260.81" y="381.844" base="387.54" width="26.3484" height="7.552">weapon</TOKEN>
</seg>
<TOKEN sid="p91_s100305" id="p91_w877" font-name="ssexcelsior" serif="yes" bold="no" italic="no" font-size="8" font-color="#000000" rotation="0" angle="0" x="288.74" y="381.844" base="387.54" width="5.9868" height="7.552">je</TOKEN>
<TOKEN sid="p91_s100306" id="p91_w878" font-name="ssexcelsior" serif="yes" bold="no" italic="no" font-size="8" font-color="#000000" rotation="0" angle="0" x="296.317" y="381.844" base="387.54" width="35.0964" height="7.552">odebeljeni</TOKEN>
<TOKEN sid="p91_s100307" id="p91_w879" font-name="ssexcelsior" serif="yes" bold="no" italic="no" font-size="8" font-color="#000000" rotation="0" angle="0" x="333.003" y="381.844" base="387.54" width="10.3752" height="7.552">del</TOKEN>
<TOKEN sid="p91_s100308" id="p91_w880" font-name="ssexcelsior" serif="yes" bold="no" italic="no" font-size="8" font-color="#000000" rotation="0" angle="0" x="344.968" y="381.844" base="387.54" width="20.9909" height="7.552">ro~aja</TOKEN>
<TOKEN sid="p91_s100309" id="p91_w881" font-name="ssexcelsior" serif="yes" bold="no" italic="no" font-size="8" font-color="#000000" rotation="0" angle="0" x="367.549" y="381.844" base="387.54" width="24.354" height="7.552">kakega</TOKEN>
<TOKEN sid="p91_s100310" id="p91_w882" font-name="ssexcelsior" serif="yes" bold="no" italic="no" font-size="8" font-color="#000000" rotation="0" angle="0" x="393.494" y="381.844" base="387.54" width="22.9817" height="7.552">oro`ja.</TOKEN>
</def>
<cit type="translationEquivalent">
<quote>
<TOKEN sid="p91_s100312" id="p91_w884" font-name="ssexcelsior" serif="yes" bold="no" italic="no" font-size="8" font-color="#000000" rotation="0" angle="0" x="423.88" y="381.844" base="387.54" width="18.347" height="7.552">kopi-</TOKEN>
<TOKEN sid="p91_s100313" id="p91_w885" font-name="ssexcelsior" serif="yes" bold="no" italic="no" font-size="8" font-color="#000000" rotation="0" angle="0" x="260.81" y="390.924" base="396.62" width="8.80128" height="7.552">to;</TOKEN>
</quote>
</cit>
<seg type="example">
<quote>
<TOKEN sid="p91_s100314" id="p91_w886" font-name="ssexcelsior" bold="no" italic="yes" font-size="8" font-color="#000000" rotation="0" angle="0" x="271.37" y="390.924" base="396.62" width="17.9978" height="7.552">…the</TOKEN>
<TOKEN sid="p91_s100315" id="p91_w887" font-name="ssexcelsior" bold="no" italic="yes" font-size="8" font-color="#000000" rotation="0" angle="0" x="291.118" y="390.924" base="396.62" width="25.1964" height="7.552">padded</TOKEN>
<TOKEN sid="p91_s100316" id="p91_w888" font-name="ssexcelsior" bold="no" italic="yes" font-size="8" font-color="#000000" rotation="0" angle="0" x="318.065" y="390.924" base="396.62" width="14.0018" height="7.552">butt</TOKEN>
<TOKEN sid="p91_s100317" id="p91_w889" font-name="ssexcelsior" bold="no" italic="yes" font-size="8" font-color="#000000" rotation="0" angle="0" x="333.817" y="390.924" base="396.62" width="6.40008" height="7.552">of</TOKEN>
<TOKEN sid="p91_s100318" id="p91_w890" font-name="ssexcelsior" bold="no" italic="yes" font-size="8" font-color="#000000" rotation="0" angle="0" x="341.968" y="390.924" base="396.62" width="10.7986" height="7.552">the</TOKEN>
<TOKEN sid="p91_s100319" id="p91_w891" font-name="ssexcelsior" bold="no" italic="yes" font-size="8" font-color="#000000" rotation="0" angle="0" x="354.517" y="390.924" base="396.62" width="15.9876" height="7.552">rifle.</TOKEN>
</quote>
</seg>
</sense>
<sense n="2">
<gramGrp>
<pos>
<TOKEN sid="p91_s100321" id="p91_w893" font-name="ssexcelsior" serif="yes" bold="no" italic="no" font-size="5.5" font-color="#000000" rotation="0" angle="0" x="378.68" y="392.704" base="396.62" width="18.9714" height="5.192">COUNT</TOKEN>
<TOKEN sid="p91_s100322" id="p91_w894" font-name="ssexcelsior" serif="yes" bold="no" italic="no" font-size="5.5" font-color="#000000" rotation="0" angle="0" x="398.857" y="392.704" base="396.62" width="4.12335" height="5.192">N</TOKEN>
</pos>
</gramGrp>
<def xml:lang="sl">
<seg type="lemma">
<TOKEN sid="p91_s100323" id="p91_w895" font-name="ssexcelsior" bold="yes" italic="no" font-size="8" font-color="#000000" rotation="0" angle="0" x="404.72" y="390.924" base="396.62" width="12.8002" height="7.552">The</TOKEN>
<TOKEN sid="p91_s100324" id="p91_w896" font-name="ssexcelsior" bold="yes" italic="no" font-size="8" font-color="#000000" rotation="0" angle="0" x="419.27" y="390.924" base="396.62" width="14.3978" height="7.552">butt</TOKEN>
<TOKEN sid="p91_s100325" id="p91_w897" font-name="ssexcelsior" bold="yes" italic="no" font-size="8" font-color="#000000" rotation="0" angle="0" x="435.419" y="390.924" base="396.62" width="6.80328" height="7.552">of</TOKEN>
<TOKEN sid="p91_s100326" id="p91_w898" font-name="ssexcelsior" bold="yes" italic="no" font-size="8" font-color="#000000" rotation="0" angle="0" x="260.81" y="399.994" base="405.69" width="4.0032" height="7.552">a</TOKEN>
<TOKEN sid="p91_s100327" id="p91_w899" font-name="ssexcelsior" bold="yes" italic="no" font-size="8" font-color="#000000" rotation="0" angle="0" x="266.323" y="399.994" base="405.69" width="29.1175" height="7.552">cigarette</TOKEN>
<TOKEN sid="p91_s100328" id="p91_w900" font-name="ssexcelsior" bold="yes" italic="no" font-size="8" font-color="#000000" rotation="0" angle="0" x="296.951" y="399.994" base="405.69" width="7.10928" height="7.552">or</TOKEN>
<TOKEN sid="p91_s100329" id="p91_w901" font-name="ssexcelsior" bold="yes" italic="no" font-size="8" font-color="#000000" rotation="0" angle="0" x="305.571" y="399.994" base="405.69" width="16.8379" height="7.552">cigar</TOKEN>
</seg>
<TOKEN sid="p91_s100330" id="p91_w902" font-name="ssexcelsior" serif="yes" bold="no" italic="no" font-size="8" font-color="#000000" rotation="0" angle="0" x="323.9" y="399.994" base="405.69" width="5.90688" height="7.552">je</TOKEN>
<TOKEN sid="p91_s100331" id="p91_w903" font-name="ssexcelsior" serif="yes" bold="no" italic="no" font-size="8" font-color="#000000" rotation="0" angle="0" x="331.318" y="399.994" base="405.69" width="22.7448" height="7.552">ko{~ek</TOKEN>
<TOKEN sid="p91_s100332" id="p91_w904" font-name="ssexcelsior" serif="yes" bold="no" italic="no" font-size="8" font-color="#000000" rotation="0" angle="0" x="355.574" y="399.994" base="405.69" width="20.1686" height="7.552">cigare</TOKEN>
<TOKEN sid="p91_s100333" id="p91_w905" font-name="ssexcelsior" serif="yes" bold="no" italic="no" font-size="8" font-color="#000000" rotation="0" angle="0" x="377.253" y="399.994" base="405.69" width="8.61696" height="7.552">ali</TOKEN>
<TOKEN sid="p91_s100334" id="p91_w906" font-name="ssexcelsior" serif="yes" bold="no" italic="no" font-size="8" font-color="#000000" rotation="0" angle="0" x="387.381" y="399.994" base="405.69" width="28.319" height="7.552">cigarete,</TOKEN>
<TOKEN sid="p91_s100335" id="p91_w907" font-name="ssexcelsior" serif="yes" bold="no" italic="no" font-size="8" font-color="#000000" rotation="0" angle="0" x="417.211" y="399.994" base="405.69" width="6.70608" height="7.552">ki</TOKEN>
<TOKEN sid="p91_s100336" id="p91_w908" font-name="ssexcelsior" serif="yes" bold="no" italic="no" font-size="8" font-color="#000000" rotation="0" angle="0" x="425.429" y="399.994" base="405.69" width="16.8379" height="7.552">osta-</TOKEN>
<TOKEN sid="p91_s100337" id="p91_w909" font-name="ssexcelsior" serif="yes" bold="no" italic="no" font-size="8" font-color="#000000" rotation="0" angle="0" x="260.81" y="409.074" base="414.77" width="9.6984" height="7.552">ne,</TOKEN>
<TOKEN sid="p91_s100338" id="p91_w910" font-name="ssexcelsior" serif="yes" bold="no" italic="no" font-size="8" font-color="#000000" rotation="0" angle="0" x="271.958" y="409.074" base="414.77" width="20.5992" height="7.552">potem</TOKEN>
<TOKEN sid="p91_s100339" id="p91_w911" font-name="ssexcelsior" serif="yes" bold="no" italic="no" font-size="8" font-color="#000000" rotation="0" angle="0" x="294.006" y="409.074" base="414.77" width="8.2512" height="7.552">ko</TOKEN>
<TOKEN sid="p91_s100340" id="p91_w912" font-name="ssexcelsior" serif="yes" bold="no" italic="no" font-size="8" font-color="#000000" rotation="0" angle="0" x="303.707" y="409.074" base="414.77" width="6.2496" height="7.552">jo</TOKEN>
<TOKEN sid="p91_s100341" id="p91_w913" font-name="ssexcelsior" serif="yes" bold="no" italic="no" font-size="8" font-color="#000000" rotation="0" angle="0" x="311.406" y="409.074" base="414.77" width="34.7976" height="7.552">pokadimo.</TOKEN>
</def>
<cit type="translationEquivalent">
<quote>
<TOKEN sid="p91_s100343" id="p91_w915" font-name="ssexcelsior" serif="yes" bold="no" italic="no" font-size="8" font-color="#000000" rotation="0" angle="0" x="353.45" y="409.074" base="414.77" width="10.0915" height="7.552">~ik</TOKEN>
</quote>
</cit>
</sense>
<sense n="3">
<gramGrp>
<pos>
<TOKEN sid="p91_s100345" id="p91_w917" font-name="ssexcelsior" serif="yes" bold="no" italic="no" font-size="5.5" font-color="#000000" rotation="0" angle="0" x="371.1" y="410.854" base="414.77" width="18.5714" height="5.192">COUNT</TOKEN>
<TOKEN sid="p91_s100346" id="p91_w918" font-name="ssexcelsior" serif="yes" bold="no" italic="no" font-size="5.5" font-color="#000000" rotation="0" angle="0" x="390.677" y="410.854" base="414.77" width="4.12335" height="5.192">N</TOKEN>
</pos>
</gramGrp>
<def xml:lang="sl">
<seg type="lemma">
<TOKEN sid="p91_s100347" id="p91_w919" font-name="ssexcelsior" bold="yes" italic="no" font-size="8" font-color="#000000" rotation="0" angle="0" x="396.28" y="409.074" base="414.77" width="5.6016" height="7.552">A</TOKEN>
<TOKEN sid="p91_s100348" id="p91_w920" font-name="ssexcelsior" bold="yes" italic="no" font-size="8" font-color="#000000" rotation="0" angle="0" x="403.332" y="409.074" base="414.77" width="13.9486" height="7.552">butt</TOKEN>
</seg>
<TOKEN sid="p91_s100349" id="p91_w921" font-name="ssexcelsior" serif="yes" bold="no" italic="no" font-size="8" font-color="#000000" rotation="0" angle="0" x="418.73" y="409.074" base="414.77" width="5.84712" height="7.552">je</TOKEN>
<TOKEN sid="p91_s100350" id="p91_w922" font-name="ssexcelsior" serif="yes" bold="no" italic="no" font-size="8" font-color="#000000" rotation="0" angle="0" x="426.028" y="409.074" base="414.77" width="16.1957" height="7.552">velik</TOKEN>
<TOKEN sid="p91_s100351" id="p91_w923" font-name="ssexcelsior" serif="yes" bold="no" italic="no" font-size="8" font-color="#000000" rotation="0" angle="0" x="260.81" y="418.154" base="423.85" width="13.5986" height="7.552">sod,</TOKEN>
<TOKEN sid="p91_s100352" id="p91_w924" font-name="ssexcelsior" serif="yes" bold="no" italic="no" font-size="8" font-color="#000000" rotation="0" angle="0" x="277.479" y="418.154" base="423.85" width="6.79608" height="7.552">ki</TOKEN>
<TOKEN sid="p91_s100353" id="p91_w925" font-name="ssexcelsior" serif="yes" bold="no" italic="no" font-size="8" font-color="#000000" rotation="0" angle="0" x="287.345" y="418.154" base="423.85" width="8.00568" height="7.552">ga</TOKEN>
<TOKEN sid="p91_s100354" id="p91_w926" font-name="ssexcelsior" serif="yes" bold="no" italic="no" font-size="8" font-color="#000000" rotation="0" angle="0" x="298.42" y="418.154" base="423.85" width="43.596" height="7.552">uporabljamo</TOKEN>
<TOKEN sid="p91_s100355" id="p91_w927" font-name="ssexcelsior" serif="yes" bold="no" italic="no" font-size="8" font-color="#000000" rotation="0" angle="0" x="345.087" y="418.154" base="423.85" width="7.60248" height="7.552">za</TOKEN>
<TOKEN sid="p91_s100356" id="p91_w928" font-name="ssexcelsior" serif="yes" bold="no" italic="no" font-size="8" font-color="#000000" rotation="0" angle="0" x="355.759" y="418.154" base="423.85" width="27.9886" height="7.552">zbiranje</TOKEN>
<TOKEN sid="p91_s100357" id="p91_w929" font-name="ssexcelsior" serif="yes" bold="no" italic="no" font-size="8" font-color="#000000" rotation="0" angle="0" x="386.818" y="418.154" base="423.85" width="8.79696" height="7.552">ali</TOKEN>
<TOKEN sid="p91_s100358" id="p91_w930" font-name="ssexcelsior" serif="yes" bold="no" italic="no" font-size="8" font-color="#000000" rotation="0" angle="0" x="398.685" y="418.154" base="423.85" width="43.5881" height="7.552">shranjevanje</TOKEN>
<TOKEN sid="p91_s100359" id="p91_w931" font-name="ssexcelsior" serif="yes" bold="no" italic="no" font-size="8" font-color="#000000" rotation="0" angle="0" x="260.81" y="427.234" base="432.93" width="30.8016" height="7.552">teko~ine.</TOKEN>
</def>
<cit type="translationEquivalent">
<quote>
<TOKEN sid="p91_s100361" id="p91_w933" font-name="ssexcelsior" serif="yes" bold="no" italic="no" font-size="8" font-color="#000000" rotation="0" angle="0" x="300.68" y="427.234" base="432.93" width="11.5963" height="7.552">sod</TOKEN>
<TOKEN sid="p91_s100362" id="p91_w934" font-name="ssexcelsior" serif="yes" bold="no" italic="no" font-size="8" font-color="#000000" rotation="0" angle="0" x="314.696" y="427.234" base="432.93" width="33.575" height="7.552">(pribli`no</TOKEN>
<TOKEN sid="p91_s100363" id="p91_w935" font-name="ssexcelsior" serif="yes" bold="no" italic="no" font-size="8" font-color="#000000" rotation="0" angle="0" x="350.69" y="427.234" base="432.93" width="12.0067" height="7.552">490</TOKEN>
<TOKEN sid="p91_s100364" id="p91_w936" font-name="ssexcelsior" serif="yes" bold="no" italic="no" font-size="8" font-color="#000000" rotation="0" angle="0" x="365.116" y="427.234" base="432.93" width="23.0494" height="7.552">litrov);</TOKEN>
</quote>
</cit>
<seg type="example">
<quote>
<TOKEN sid="p91_s100365" id="p91_w937" font-name="ssexcelsior" bold="no" italic="yes" font-size="8" font-color="#000000" rotation="0" angle="0" x="390.59" y="427.234" base="432.93" width="11.2025" height="7.552">…a</TOKEN>
<TOKEN sid="p91_s100366" id="p91_w938" font-name="ssexcelsior" bold="no" italic="yes" font-size="8" font-color="#000000" rotation="0" angle="0" x="404.212" y="427.234" base="432.93" width="19.5955" height="7.552">water</TOKEN>
<TOKEN sid="p91_s100367" id="p91_w939" font-name="ssexcelsior" bold="no" italic="yes" font-size="8" font-color="#000000" rotation="0" angle="0" x="426.228" y="427.234" base="432.93" width="16.0027" height="7.552">butt.</TOKEN>
</quote>
</seg>
</sense>
<sense n="4">
<gramGrp>
<pos>
<TOKEN sid="p91_s100369" id="p91_w941" font-name="ssexcelsior" serif="yes" bold="no" italic="no" font-size="5.5" font-color="#000000" rotation="0" angle="0" x="267.75" y="438.094" base="442.01" width="13.4724" height="5.192">SING</TOKEN>
<TOKEN sid="p91_s100370" id="p91_w942" font-name="ssexcelsior" serif="yes" bold="no" italic="no" font-size="5.5" font-color="#000000" rotation="0" angle="0" x="282.778" y="438.094" base="442.01" width="4.12335" height="5.192">N</TOKEN>
</pos>
</gramGrp>
<def xml:lang="sl">
<seg type="lemma">
<TOKEN sid="p91_s100371" id="p91_w943" font-name="ssexcelsior" bold="yes" italic="no" font-size="8" font-color="#000000" rotation="0" angle="0" x="289.17" y="436.314" base="442.01" width="8.1432" height="7.552">To</TOKEN>
<TOKEN sid="p91_s100372" id="p91_w944" font-name="ssexcelsior" bold="yes" italic="no" font-size="8" font-color="#000000" rotation="0" angle="0" x="299.583" y="436.314" base="442.01" width="7.99848" height="7.552">be</TOKEN>
<TOKEN sid="p91_s100373" id="p91_w945" font-name="ssexcelsior" bold="yes" italic="no" font-size="8" font-color="#000000" rotation="0" angle="0" x="309.852" y="436.314" base="442.01" width="10.7986" height="7.552">the</TOKEN>
<TOKEN sid="p91_s100374" id="p91_w946" font-name="ssexcelsior" bold="yes" italic="no" font-size="8" font-color="#000000" rotation="0" angle="0" x="322.921" y="436.314" base="442.01" width="14.3978" height="7.552">butt</TOKEN>
<TOKEN sid="p91_s100375" id="p91_w947" font-name="ssexcelsior" bold="yes" italic="no" font-size="8" font-color="#000000" rotation="0" angle="0" x="339.589" y="436.314" base="442.01" width="6.80328" height="7.552">of</TOKEN>
<TOKEN sid="p91_s100376" id="p91_w948" font-name="ssexcelsior" bold="yes" italic="no" font-size="8" font-color="#000000" rotation="0" angle="0" x="348.662" y="436.314" base="442.01" width="24.3965" height="7.552">teasing</TOKEN>
<TOKEN sid="p91_s100377" id="p91_w949" font-name="ssexcelsior" bold="yes" italic="no" font-size="8" font-color="#000000" rotation="0" angle="0" x="375.329" y="436.314" base="442.01" width="7.19928" height="7.552">or</TOKEN>
<TOKEN sid="p91_s100378" id="p91_w950" font-name="ssexcelsior" bold="yes" italic="no" font-size="8" font-color="#000000" rotation="0" angle="0" x="384.798" y="436.314" base="442.01" width="29.9822" height="7.552">criticism</TOKEN>
</seg>
<TOKEN sid="p91_s100379" id="p91_w951" font-name="ssexcelsior" serif="yes" bold="no" italic="no" font-size="8" font-color="#000000" rotation="0" angle="0" x="417.03" y="436.314" base="442.01" width="25.1892" height="7.552">pomeni</TOKEN>
<TOKEN sid="p91_s100380" id="p91_w952" font-name="ssexcelsior" serif="yes" bold="no" italic="no" font-size="8" font-color="#000000" rotation="0" angle="0" x="260.81" y="445.394" base="451.09" width="11.3926" height="7.552">biti</TOKEN>
<TOKEN sid="p91_s100381" id="p91_w953" font-name="ssexcelsior" serif="yes" bold="no" italic="no" font-size="8" font-color="#000000" rotation="0" angle="0" x="273.603" y="445.394" base="451.09" width="16.2778" height="7.552">`rtev</TOKEN>
<TOKEN sid="p91_s100382" id="p91_w954" font-name="ssexcelsior" serif="yes" bold="no" italic="no" font-size="8" font-color="#000000" rotation="0" angle="0" x="291.28" y="445.394" base="451.09" width="16.9884" height="7.552">ljudi,</TOKEN>
<TOKEN sid="p91_s100383" id="p91_w955" font-name="ssexcelsior" serif="yes" bold="no" italic="no" font-size="8" font-color="#000000" rotation="0" angle="0" x="309.668" y="445.394" base="451.09" width="6.59592" height="7.552">ki</TOKEN>
<TOKEN sid="p91_s100384" id="p91_w956" font-name="ssexcelsior" serif="yes" bold="no" italic="no" font-size="8" font-color="#000000" rotation="0" angle="0" x="317.664" y="445.394" base="451.09" width="11.1974" height="7.552">nas</TOKEN>
<TOKEN sid="p91_s100385" id="p91_w957" font-name="ssexcelsior" serif="yes" bold="no" italic="no" font-size="8" font-color="#000000" rotation="0" angle="0" x="330.261" y="445.394" base="451.09" width="22.7923" height="7.552">dra`ijo</TOKEN>
<TOKEN sid="p91_s100386" id="p91_w958" font-name="ssexcelsior" serif="yes" bold="no" italic="no" font-size="8" font-color="#000000" rotation="0" angle="0" x="354.453" y="445.394" base="451.09" width="8.39592" height="7.552">ali</TOKEN>
<TOKEN sid="p91_s100387" id="p91_w959" font-name="ssexcelsior" serif="yes" bold="no" italic="no" font-size="8" font-color="#000000" rotation="0" angle="0" x="364.249" y="445.394" base="451.09" width="34.5823" height="7.552">kritizirajo.</TOKEN>
</def>
<cit type="translationEquivalent">
<quote>
<TOKEN sid="p91_s100389" id="p91_w961" font-name="ssexcelsior" serif="yes" bold="no" italic="no" font-size="8" font-color="#000000" rotation="0" angle="0" x="406.12" y="445.394" base="451.09" width="18.4694" height="7.552">tar~a;</TOKEN>
</quote>
</cit>
<seg type="example">
<quote>
<TOKEN sid="p91_s100390" id="p91_w962" font-name="ssexcelsior" bold="no" italic="yes" font-size="8" font-color="#000000" rotation="0" angle="0" x="426.01" y="445.394" base="451.09" width="16.2" height="7.552">They</TOKEN>
<TOKEN sid="p91_s100391" id="p91_w963" font-name="ssexcelsior" bold="no" italic="yes" font-size="8" font-color="#000000" rotation="0" angle="0" x="260.81" y="454.474" base="460.17" width="18.401" height="7.552">made</TOKEN>
<TOKEN sid="p91_s100392" id="p91_w964" font-name="ssexcelsior" bold="no" italic="yes" font-size="8" font-color="#000000" rotation="0" angle="0" x="281.411" y="454.474" base="460.17" width="13.1962" height="7.552">him</TOKEN>
<TOKEN sid="p91_s100393" id="p91_w965" font-name="ssexcelsior" bold="no" italic="yes" font-size="8" font-color="#000000" rotation="0" angle="0" x="296.807" y="454.474" base="460.17" width="10.7986" height="7.552">the</TOKEN>
<TOKEN sid="p91_s100394" id="p91_w966" font-name="ssexcelsior" bold="no" italic="yes" font-size="8" font-color="#000000" rotation="0" angle="0" x="309.806" y="454.474" base="460.17" width="14.0018" height="7.552">butt</TOKEN>
<TOKEN sid="p91_s100395" id="p91_w967" font-name="ssexcelsior" bold="no" italic="yes" font-size="8" font-color="#000000" rotation="0" angle="0" x="326.008" y="454.474" base="460.17" width="6.40008" height="7.552">of</TOKEN>
<TOKEN sid="p91_s100396" id="p91_w968" font-name="ssexcelsior" bold="no" italic="yes" font-size="8" font-color="#000000" rotation="0" angle="0" x="334.608" y="454.474" base="460.17" width="24.7853" height="7.552">endless</TOKEN>
<TOKEN sid="p91_s100397" id="p91_w969" font-name="ssexcelsior" bold="no" italic="yes" font-size="8" font-color="#000000" rotation="0" angle="0" x="361.593" y="454.474" base="460.17" width="30.3926" height="7.552">practical</TOKEN>
<TOKEN sid="p91_s100398" id="p91_w970" font-name="ssexcelsior" bold="no" italic="yes" font-size="8" font-color="#000000" rotation="0" angle="0" x="394.186" y="454.474" base="460.17" width="19.5948" height="7.552">jokes.</TOKEN>
</quote>
</seg>
</sense>
<sense n="5">
<gramGrp>
<pos>
<TOKEN sid="p91_s100400" id="p91_w972" font-name="ssexcelsior" serif="yes" bold="no" italic="no" font-size="5.5" font-color="#000000" rotation="0" angle="0" x="422.85" y="456.254" base="460.17" width="7.14681" height="5.192">VB</TOKEN>
<seg>
<TOKEN sid="p91_s100401" id="p91_w973" font-name="ssexcelsior" serif="yes" bold="no" italic="no" font-size="5.5" font-color="#000000" rotation="0" angle="0" x="431.511" y="456.254" base="460.17" width="10.7187" height="5.192">with</TOKEN>
</seg>
<TOKEN sid="p91_s100402" id="p91_w974" font-name="ssexcelsior" serif="yes" bold="no" italic="no" font-size="5.5" font-color="#000000" rotation="0" angle="0" x="260.81" y="465.324" base="469.24" width="9.9" height="5.192">OBJ</TOKEN>
</pos>
</gramGrp>
<def xml:lang="sl">
<seg type="lemma">
<TOKEN sid="p91_s100403" id="p91_w975" font-name="ssexcelsior" bold="yes" italic="no" font-size="8" font-color="#000000" rotation="0" angle="0" x="273.58" y="463.544" base="469.24" width="8.15328" height="7.552">To</TOKEN>
<TOKEN sid="p91_s100404" id="p91_w976" font-name="ssexcelsior" bold="yes" italic="no" font-size="8" font-color="#000000" rotation="0" angle="0" x="284.602" y="463.544" base="469.24" width="14.3957" height="7.552">butt</TOKEN>
<TOKEN sid="p91_s100405" id="p91_w977" font-name="ssexcelsior" bold="yes" italic="no" font-size="8" font-color="#000000" rotation="0" angle="0" x="301.867" y="463.544" base="469.24" width="35.1893" height="7.552">something</TOKEN>
</seg>
<TOKEN sid="p91_s100406" id="p91_w978" font-name="ssexcelsior" serif="yes" bold="no" italic="no" font-size="8" font-color="#000000" rotation="0" angle="0" x="339.94" y="463.544" base="469.24" width="25.1964" height="7.552">pomeni</TOKEN>
<TOKEN sid="p91_s100407" id="p91_w979" font-name="ssexcelsior" serif="yes" bold="no" italic="no" font-size="8" font-color="#000000" rotation="0" angle="0" x="368.007" y="463.544" base="469.24" width="18.7963" height="7.552">nekaj</TOKEN>
<TOKEN sid="p91_s100408" id="p91_w980" font-name="ssexcelsior" serif="yes" bold="no" italic="no" font-size="8" font-color="#000000" rotation="0" angle="0" x="389.673" y="463.544" base="469.24" width="22.4035" height="7.552">mo~no</TOKEN>
<TOKEN sid="p91_s100409" id="p91_w981" font-name="ssexcelsior" serif="yes" bold="no" italic="no" font-size="8" font-color="#000000" rotation="0" angle="0" x="414.946" y="463.544" base="469.24" width="20.7972" height="7.552">zadeti</TOKEN>
<TOKEN sid="p91_s100410" id="p91_w982" font-name="ssexcelsior" serif="yes" bold="no" italic="no" font-size="8" font-color="#000000" rotation="0" angle="0" x="438.613" y="463.544" base="469.24" width="3.6" height="7.552">z</TOKEN>
<TOKEN sid="p91_s100411" id="p91_w983" font-name="ssexcelsior" serif="yes" bold="no" italic="no" font-size="8" font-color="#000000" rotation="0" angle="0" x="260.81" y="472.624" base="478.32" width="20.4084" height="7.552">glavo.</TOKEN>
</def>
<cit type="translationEquivalent">
<quote>
<TOKEN sid="p91_s100413" id="p91_w985" font-name="ssexcelsior" serif="yes" bold="no" italic="no" font-size="8" font-color="#000000" rotation="0" angle="0" x="289.45" y="472.624" base="478.32" width="19.584" height="7.552">suniti</TOKEN>
<TOKEN sid="p91_s100414" id="p91_w986" font-name="ssexcelsior" serif="yes" bold="no" italic="no" font-size="8" font-color="#000000" rotation="0" angle="0" x="311.033" y="472.624" base="478.32" width="3.6" height="7.552">z</TOKEN>
<TOKEN sid="p91_s100415" id="p91_w987" font-name="ssexcelsior" serif="yes" bold="no" italic="no" font-size="8" font-color="#000000" rotation="0" angle="0" x="316.631" y="472.624" base="478.32" width="20.4048" height="7.552">glavo;</TOKEN>
</quote>
</cit>
<seg type="example">
<quote>
<TOKEN sid="p91_s100416" id="p91_w988" font-name="ssexcelsior" bold="no" italic="yes" font-size="8" font-color="#000000" rotation="0" angle="0" x="339.04" y="472.624" base="478.32" width="9.59688" height="7.552">He</TOKEN>
<TOKEN sid="p91_s100417" id="p91_w989" font-name="ssexcelsior" bold="no" italic="yes" font-size="8" font-color="#000000" rotation="0" angle="0" x="350.637" y="472.624" base="478.32" width="21.9996" height="7.552">butted</TOKEN>
<TOKEN sid="p91_s100418" id="p91_w990" font-name="ssexcelsior" bold="no" italic="yes" font-size="8" font-color="#000000" rotation="0" angle="0" x="374.637" y="472.624" base="478.32" width="21.9996" height="7.552">Stuart</TOKEN>
<TOKEN sid="p91_s100419" id="p91_w991" font-name="ssexcelsior" bold="no" italic="yes" font-size="8" font-color="#000000" rotation="0" angle="0" x="398.637" y="472.624" base="478.32" width="6.79608" height="7.552">in</TOKEN>
<TOKEN sid="p91_s100420" id="p91_w992" font-name="ssexcelsior" bold="no" italic="yes" font-size="8" font-color="#000000" rotation="0" angle="0" x="407.433" y="472.624" base="478.32" width="10.7986" height="7.552">the</TOKEN>
<TOKEN sid="p91_s100421" id="p91_w993" font-name="ssexcelsior" bold="no" italic="yes" font-size="8" font-color="#000000" rotation="0" angle="0" x="420.232" y="472.624" base="478.32" width="19.5948" height="7.552">chest.</TOKEN>
</quote>
</seg>
</sense>
<sense value="phr vb">
<form type="lemma">
<orth>
<TOKEN sid="p91_s100422" id="p91_w994" font-name="ssunivers" serif="yes" fixed-width="yes" bold="yes" italic="no" font-size="8" font-color="#000000" rotation="0" angle="0" x="260.81" y="481.704" base="487.4" width="14.0674" height="7.568">butt</TOKEN>
<TOKEN sid="p91_s100423" id="p91_w995" font-name="ssunivers" serif="yes" fixed-width="yes" bold="yes" italic="no" font-size="8" font-color="#000000" rotation="0" angle="0" x="276.368" y="481.704" base="487.4" width="8.18064" height="7.568">in.</TOKEN>
</orth>
</form>
<gramGrp>
<pos>
<TOKEN sid="p91_s100424" id="p91_w996" font-name="ssexcelsior" serif="yes" bold="no" italic="no" font-size="5.5" font-color="#000000" rotation="0" angle="0" x="286.02" y="483.484" base="487.4" width="10.8375" height="5.192">PHR</TOKEN>
<TOKEN sid="p91_s100425" id="p91_w997" font-name="ssexcelsior" serif="yes" bold="no" italic="no" font-size="5.5" font-color="#000000" rotation="0" angle="0" x="297.873" y="483.484" base="487.4" width="7.06712" height="5.192">VB</TOKEN>
</pos>
</gramGrp>
<sense>
<def xml:lang="sl">
<seg type="lemma">
<TOKEN sid="p91_s100426" id="p91_w998" font-name="ssexcelsior" bold="yes" italic="no" font-size="8" font-color="#000000" rotation="0" angle="0" x="306.48" y="481.704" base="487.4" width="8.02296" height="7.552">To</TOKEN>
<TOKEN sid="p91_s100427" id="p91_w999" font-name="ssexcelsior" bold="yes" italic="no" font-size="8" font-color="#000000" rotation="0" angle="0" x="315.991" y="481.704" base="487.4" width="14.0652" height="7.552">butt</TOKEN>
<TOKEN sid="p91_s100428" id="p91_w1000" font-name="ssexcelsior" bold="yes" italic="no" font-size="8" font-color="#000000" rotation="0" angle="0" x="331.545" y="481.704" base="487.4" width="6.6852" height="7.552">in</TOKEN>
</seg>
<TOKEN sid="p91_s100429" id="p91_w1001" font-name="ssexcelsior" serif="yes" bold="no" italic="no" font-size="8" font-color="#000000" rotation="0" angle="0" x="339.71" y="481.704" base="487.4" width="24.642" height="7.552">pomeni</TOKEN>
<TOKEN sid="p91_s100430" id="p91_w1002" font-name="ssexcelsior" serif="yes" bold="no" italic="no" font-size="8" font-color="#000000" rotation="0" angle="0" x="365.84" y="481.704" base="487.4" width="33.1128" height="7.552">neotesano</TOKEN>
<TOKEN sid="p91_s100431" id="p91_w1003" font-name="ssexcelsior" serif="yes" bold="no" italic="no" font-size="8" font-color="#000000" rotation="0" angle="0" x="400.441" y="481.704" base="487.4" width="6.6852" height="7.552">se</TOKEN>
<TOKEN sid="p91_s100432" id="p91_w1004" font-name="ssexcelsior" serif="yes" bold="no" italic="no" font-size="8" font-color="#000000" rotation="0" angle="0" x="408.615" y="481.704" base="487.4" width="33.6672" height="7.552">priklju~iti</TOKEN>
<TOKEN sid="p91_s100433" id="p91_w1005" font-name="ssexcelsior" serif="yes" bold="no" italic="no" font-size="8" font-color="#000000" rotation="0" angle="0" x="260.81" y="490.784" base="496.48" width="37.5926" height="7.552">zasebnemu</TOKEN>
<TOKEN sid="p91_s100434" id="p91_w1006" font-name="ssexcelsior" serif="yes" bold="no" italic="no" font-size="8" font-color="#000000" rotation="0" angle="0" x="300.683" y="490.784" base="496.48" width="32.0062" height="7.552">pogovoru</TOKEN>
<TOKEN sid="p91_s100435" id="p91_w1007" font-name="ssexcelsior" serif="yes" bold="no" italic="no" font-size="8" font-color="#000000" rotation="0" angle="0" x="334.969" y="490.784" base="496.48" width="8.79696" height="7.552">ali</TOKEN>
<TOKEN sid="p91_s100436" id="p91_w1008" font-name="ssexcelsior" serif="yes" bold="no" italic="no" font-size="8" font-color="#000000" rotation="0" angle="0" x="346.046" y="490.784" base="496.48" width="37.1952" height="7.552">dejavnosti,</TOKEN>
<TOKEN sid="p91_s100437" id="p91_w1009" font-name="ssexcelsior" serif="yes" bold="no" italic="no" font-size="8" font-color="#000000" rotation="0" angle="0" x="385.522" y="490.784" base="496.48" width="7.99848" height="7.552">ne</TOKEN>
<TOKEN sid="p91_s100438" id="p91_w1010" font-name="ssexcelsior" serif="yes" bold="no" italic="no" font-size="8" font-color="#000000" rotation="0" angle="0" x="395.8" y="490.784" base="496.48" width="8.40168" height="7.552">da</TOKEN>
<TOKEN sid="p91_s100439" id="p91_w1011" font-name="ssexcelsior" serif="yes" bold="no" italic="no" font-size="8" font-color="#000000" rotation="0" angle="0" x="406.482" y="490.784" base="496.48" width="6.79608" height="7.552">bi</TOKEN>
<TOKEN sid="p91_s100440" id="p91_w1012" font-name="ssexcelsior" serif="yes" bold="no" italic="no" font-size="8" font-color="#000000" rotation="0" angle="0" x="415.558" y="490.784" base="496.48" width="11.5978" height="7.552">nas</TOKEN>
<TOKEN sid="p91_s100441" id="p91_w1013" font-name="ssexcelsior" serif="yes" bold="no" italic="no" font-size="8" font-color="#000000" rotation="0" angle="0" x="429.436" y="490.784" base="496.48" width="12.8002" height="7.552">kdo</TOKEN>
<TOKEN sid="p91_s100442" id="p91_w1014" font-name="ssexcelsior" serif="yes" bold="no" italic="no" font-size="8" font-color="#000000" rotation="0" angle="0" x="260.81" y="499.864" base="505.56" width="27.5998" height="7.552">povabil.</TOKEN>
</def>
<cit type="translationEquivalent">
<quote>
<TOKEN sid="p91_s100444" id="p91_w1016" font-name="ssexcelsior" serif="yes" bold="no" italic="no" font-size="8" font-color="#000000" rotation="0" angle="0" x="296.64" y="499.864" base="505.56" width="26.3938" height="7.552">vme{ati</TOKEN>
<TOKEN sid="p91_s100445" id="p91_w1017" font-name="ssexcelsior" serif="yes" bold="no" italic="no" font-size="8" font-color="#000000" rotation="0" angle="0" x="325.032" y="499.864" base="505.56" width="8.79552" height="7.552">se;</TOKEN>
</quote>
</cit>
</sense>
</sense>
</sense>
</entry>
