<entry xml:lang="en">
<form type="lemma">
<orth>
<TOKEN sid="p731_s804032" id="p731_w496" font-name="ssunivers" fixed-width="yes" bold="yes" italic="no" font-size="9" font-color="#000000" rotation="0" angle="0" x="56.72" y="589.942" base="596.35" width="23.5168" height="8.514">squirt</TOKEN>
</orth>
<form type="variant">
<pron>
<TOKEN sid="p731_s804033" id="p731_w497" font-name="ssexcelsior" symbolic="yes" bold="no" italic="no" font-size="7.25" font-color="#000000" rotation="0" angle="0" x="81.79" y="591.188" base="596.35" width="29.6316" height="6.844">/skw&#197;&#194;t/,</TOKEN>
</pron>
</form>
<form type="inflected">
<TOKEN sid="p731_s804034" id="p731_w498" font-name="ssunivers" symbolic="yes" bold="no" italic="no" font-size="7.5" font-color="#000000" rotation="0" angle="0" x="112.97" y="591.01" base="596.35" width="23.3415" height="7.08">squirts,</TOKEN>
<TOKEN sid="p731_s804035" id="p731_w499" font-name="ssunivers" symbolic="yes" bold="no" italic="no" font-size="7.5" font-color="#000000" rotation="0" angle="0" x="137.777" y="591.01" base="596.35" width="30.0105" height="7.08">squirting,</TOKEN>
<TOKEN sid="p731_s804036" id="p731_w500" font-name="ssunivers" symbolic="yes" bold="no" italic="no" font-size="7.5" font-color="#000000" rotation="0" angle="0" x="169.253" y="591.01" base="596.35" width="27.8033" height="7.08">squirted.</TOKEN>
</form>
</form>
<sense>
<gramGrp>
<pos>
<TOKEN sid="p731_s804037" id="p731_w501" font-name="ssexcelsior" symbolic="yes" bold="no" italic="no" font-size="5.5" font-color="#000000" rotation="0" angle="0" x="198.54" y="592.434" base="596.35" width="11.2098" height="5.192">ERG</TOKEN>
<TOKEN sid="p731_s804038" id="p731_w502" font-name="ssexcelsior" symbolic="yes" bold="no" italic="no" font-size="5.5" font-color="#000000" rotation="0" angle="0" x="210.824" y="592.434" base="596.35" width="7.11711" height="5.192">VB</TOKEN>
<seg>
<TOKEN sid="p731_s804039" id="p731_w503" font-name="ssexcelsior" symbolic="yes" bold="no" italic="no" font-size="5.5" font-color="#000000" rotation="0" angle="0" x="219.016" y="592.434" base="596.35" width="4.91931" height="5.192">or</TOKEN>
</seg>
<TOKEN sid="p731_s804040" id="p731_w504" font-name="ssexcelsior" symbolic="yes" bold="no" italic="no" font-size="5.5" font-color="#000000" rotation="0" angle="0" x="225.01" y="592.434" base="596.35" width="7.11711" height="5.192">VB</TOKEN>
<seg>
<TOKEN sid="p731_s804041" id="p731_w505" font-name="ssexcelsior" symbolic="yes" bold="no" italic="no" font-size="5.5" font-color="#000000" rotation="0" angle="0" x="233.202" y="592.434" base="596.35" width="10.6296" height="5.192">with</TOKEN>
</seg>
<TOKEN sid="p731_s804042" id="p731_w506" font-name="ssexcelsior" symbolic="yes" bold="no" italic="no" font-size="5.5" font-color="#000000" rotation="0" angle="0" x="62.3898" y="601.514" base="605.43" width="9.9" height="5.192">OBJ</TOKEN>
</pos>
</gramGrp>
<def xml:lang="sl">
<seg type="lemma">
<TOKEN sid="p731_s804043" id="p731_w507" font-name="ssexcelsior" bold="yes" italic="no" font-size="8" font-color="#000000" rotation="0" angle="0" x="74.3" y="599.734" base="605.43" width="8.1432" height="7.552">To</TOKEN>
<TOKEN sid="p731_s804044" id="p731_w508" font-name="ssexcelsior" bold="yes" italic="no" font-size="8" font-color="#000000" rotation="0" angle="0" x="84.4441" y="599.734" base="605.43" width="20.25" height="7.552">squirt</TOKEN>
<TOKEN sid="p731_s804045" id="p731_w509" font-name="ssexcelsior" bold="yes" italic="no" font-size="8" font-color="#000000" rotation="0" angle="0" x="106.696" y="599.734" base="605.43" width="4.0032" height="7.552">a</TOKEN>
<TOKEN sid="p731_s804046" id="p731_w510" font-name="ssexcelsior" bold="yes" italic="no" font-size="8" font-color="#000000" rotation="0" angle="0" x="112.718" y="599.734" base="605.43" width="20.3904" height="7.552">liquid</TOKEN>
<TOKEN sid="p731_s804047" id="p731_w511" font-name="ssexcelsior" bold="yes" italic="no" font-size="8" font-color="#000000" rotation="0" angle="0" x="135.11" y="599.734" base="605.43" width="37.854" height="7.552">somewhere</TOKEN>
</seg>
<TOKEN sid="p731_s804048" id="p731_w512" font-name="ssexcelsior" symbolic="yes" bold="no" italic="no" font-size="8" font-color="#000000" rotation="0" angle="0" x="174.98" y="599.734" base="605.43" width="27.2016" height="7.552">pomeni,</TOKEN>
<TOKEN sid="p731_s804049" id="p731_w513" font-name="ssexcelsior" symbolic="yes" bold="no" italic="no" font-size="8" font-color="#000000" rotation="0" angle="0" x="204.183" y="599.734" base="605.43" width="8.4024" height="7.552">da</TOKEN>
<TOKEN sid="p731_s804050" id="p731_w514" font-name="ssexcelsior" symbolic="yes" bold="no" italic="no" font-size="8" font-color="#000000" rotation="0" angle="0" x="214.587" y="599.734" base="605.43" width="29.2032" height="7.552">teko~ina</TOKEN>
<TOKEN sid="p731_s804051" id="p731_w515" font-name="ssexcelsior" symbolic="yes" bold="no" italic="no" font-size="8" font-color="#000000" rotation="0" angle="0" x="62.3898" y="608.804" base="614.5" width="17.7077" height="7.552">pride</TOKEN>
<TOKEN sid="p731_s804052" id="p731_w516" font-name="ssexcelsior" symbolic="yes" bold="no" italic="no" font-size="8" font-color="#000000" rotation="0" angle="0" x="81.6267" y="608.804" base="614.5" width="8.33112" height="7.552">na</TOKEN>
<TOKEN sid="p731_s804053" id="p731_w517" font-name="ssexcelsior" symbolic="yes" bold="no" italic="no" font-size="8" font-color="#000000" rotation="0" angle="0" x="91.4871" y="608.804" base="614.5" width="14.9854" height="7.552">plan</TOKEN>
<TOKEN sid="p731_s804054" id="p731_w518" font-name="ssexcelsior" symbolic="yes" bold="no" italic="no" font-size="8" font-color="#000000" rotation="0" angle="0" x="108.002" y="608.804" base="614.5" width="4.0032" height="7.552">v</TOKEN>
<TOKEN sid="p731_s804055" id="p731_w519" font-name="ssexcelsior" symbolic="yes" bold="no" italic="no" font-size="8" font-color="#000000" rotation="0" angle="0" x="113.535" y="608.804" base="614.5" width="23.6484" height="7.552">ozkem,</TOKEN>
<TOKEN sid="p731_s804056" id="p731_w520" font-name="ssexcelsior" symbolic="yes" bold="no" italic="no" font-size="8" font-color="#000000" rotation="0" angle="0" x="138.713" y="608.804" base="614.5" width="22.3099" height="7.552">hitrem</TOKEN>
<TOKEN sid="p731_s804057" id="p731_w521" font-name="ssexcelsior" symbolic="yes" bold="no" italic="no" font-size="8" font-color="#000000" rotation="0" angle="0" x="162.552" y="608.804" base="614.5" width="19.7093" height="7.552">curku</TOKEN>
<TOKEN sid="p731_s804058" id="p731_w522" font-name="ssexcelsior" symbolic="yes" bold="no" italic="no" font-size="8" font-color="#000000" rotation="0" angle="0" x="183.79" y="608.804" base="614.5" width="17.3117" height="7.552">skozi</TOKEN>
<TOKEN sid="p731_s804059" id="p731_w523" font-name="ssexcelsior" symbolic="yes" bold="no" italic="no" font-size="8" font-color="#000000" rotation="0" angle="0" x="202.631" y="608.804" base="614.5" width="15.7918" height="7.552">ozko</TOKEN>
<TOKEN sid="p731_s804060" id="p731_w524" font-name="ssexcelsior" symbolic="yes" bold="no" italic="no" font-size="8" font-color="#000000" rotation="0" angle="0" x="219.952" y="608.804" base="614.5" width="23.837" height="7.552">odprti-</TOKEN>
<TOKEN sid="p731_s804061" id="p731_w525" font-name="ssexcelsior" symbolic="yes" bold="no" italic="no" font-size="8" font-color="#000000" rotation="0" angle="0" x="260.81" y="64.0948" base="69.7908" width="10.1808" height="7.552">no.</TOKEN>
</def>
<cit type="translationEquivalent">
<quote>
<TOKEN sid="p731_s804063" id="p731_w527" font-name="ssexcelsior" symbolic="yes" bold="no" italic="no" font-size="8" font-color="#000000" rotation="0" angle="0" x="278.27" y="64.094" base="69.79" width="27.9072" height="7.552">brizgati,</TOKEN>
<TOKEN sid="p731_s804064" id="p731_w528" font-name="ssexcelsior" symbolic="yes" bold="no" italic="no" font-size="8" font-color="#000000" rotation="0" angle="0" x="307.666" y="64.094" base="69.79" width="23.1077" height="7.552">{trcati;</TOKEN>
</quote>
</cit>
<seg type="example">
<quote>
<TOKEN sid="p731_s804065" id="p731_w529" font-name="ssexcelsior" bold="no" italic="yes" font-size="8" font-color="#000000" rotation="0" angle="0" x="332.28" y="64.094" base="69.79" width="21.042" height="7.552">Squirt</TOKEN>
<TOKEN sid="p731_s804066" id="p731_w530" font-name="ssexcelsior" bold="no" italic="yes" font-size="8" font-color="#000000" rotation="0" angle="0" x="354.811" y="64.094" base="69.79" width="4.0032" height="7.552">a</TOKEN>
<TOKEN sid="p731_s804067" id="p731_w531" font-name="ssexcelsior" bold="no" italic="yes" font-size="8" font-color="#000000" rotation="0" angle="0" x="360.323" y="64.094" base="69.79" width="15.8364" height="7.552">little</TOKEN>
<TOKEN sid="p731_s804068" id="p731_w532" font-name="ssexcelsior" bold="no" italic="yes" font-size="8" font-color="#000000" rotation="0" angle="0" x="377.648" y="64.094" base="69.79" width="8.5752" height="7.552">oil</TOKEN>
<TOKEN sid="p731_s804069" id="p731_w533" font-name="ssexcelsior" bold="no" italic="yes" font-size="8" font-color="#000000" rotation="0" angle="0" x="387.711" y="64.094" base="69.79" width="13.266" height="7.552">into</TOKEN>
<TOKEN sid="p731_s804070" id="p731_w534" font-name="ssexcelsior" bold="no" italic="yes" font-size="8" font-color="#000000" rotation="0" angle="0" x="402.466" y="64.094" base="69.79" width="10.5768" height="7.552">the</TOKEN>
<TOKEN sid="p731_s804071" id="p731_w535" font-name="ssexcelsior" bold="no" italic="yes" font-size="8" font-color="#000000" rotation="0" angle="0" x="414.531" y="64.094" base="69.79" width="27.6228" height="7.552">keyhole.</TOKEN>
</quote>
<quote>
<TOKEN sid="p731_s804072" id="p731_w536" font-name="ssexcelsior" bold="no" italic="yes" font-size="8" font-color="#000000" rotation="0" angle="0" x="260.81" y="73.174" base="78.87" width="19.3572" height="7.552">Water</TOKEN>
<TOKEN sid="p731_s804073" id="p731_w537" font-name="ssexcelsior" bold="no" italic="yes" font-size="8" font-color="#000000" rotation="0" angle="0" x="281.617" y="73.174" base="78.87" width="26.9352" height="7.552">squirted</TOKEN>
<TOKEN sid="p731_s804074" id="p731_w538" font-name="ssexcelsior" bold="no" italic="yes" font-size="8" font-color="#000000" rotation="0" angle="0" x="310.001" y="73.174" base="78.87" width="10.9008" height="7.552">out</TOKEN>
<TOKEN sid="p731_s804075" id="p731_w539" font-name="ssexcelsior" bold="no" italic="yes" font-size="8" font-color="#000000" rotation="0" angle="0" x="322.351" y="73.174" base="78.87" width="6.2496" height="7.552">of</TOKEN>
<TOKEN sid="p731_s804076" id="p731_w540" font-name="ssexcelsior" bold="no" italic="yes" font-size="8" font-color="#000000" rotation="0" angle="0" x="330.05" y="73.174" base="78.87" width="4.0032" height="7.552">a</TOKEN>
<TOKEN sid="p731_s804077" id="p731_w541" font-name="ssexcelsior" bold="no" italic="yes" font-size="8" font-color="#000000" rotation="0" angle="0" x="335.483" y="73.174" base="78.87" width="13.9464" height="7.552">hole</TOKEN>
<TOKEN sid="p731_s804078" id="p731_w542" font-name="ssexcelsior" bold="no" italic="yes" font-size="8" font-color="#000000" rotation="0" angle="0" x="350.879" y="73.174" base="78.87" width="6.6456" height="7.552">in</TOKEN>
<TOKEN sid="p731_s804079" id="p731_w543" font-name="ssexcelsior" bold="no" italic="yes" font-size="8" font-color="#000000" rotation="0" angle="0" x="358.974" y="73.174" base="78.87" width="10.4976" height="7.552">the</TOKEN>
<TOKEN sid="p731_s804080" id="p731_w544" font-name="ssexcelsior" bold="no" italic="yes" font-size="8" font-color="#000000" rotation="0" angle="0" x="370.921" y="73.174" base="78.87" width="16.1928" height="7.552">pipe.</TOKEN>
</quote>
<quote>
<TOKEN sid="p731_s804081" id="p731_w545" font-name="ssexcelsior" bold="no" italic="yes" font-size="8" font-color="#000000" rotation="0" angle="0" x="388.544" y="73.174" base="78.87" width="13.6944" height="7.552">One</TOKEN>
<TOKEN sid="p731_s804082" id="p731_w546" font-name="ssexcelsior" bold="no" italic="yes" font-size="8" font-color="#000000" rotation="0" angle="0" x="403.688" y="73.174" base="78.87" width="24.1992" height="7.552">woman</TOKEN>
<TOKEN sid="p731_s804083" id="p731_w547" font-name="ssexcelsior" bold="no" italic="yes" font-size="8" font-color="#000000" rotation="0" angle="0" x="429.336" y="73.174" base="78.87" width="12.8952" height="7.552">was</TOKEN>
<TOKEN sid="p731_s804084" id="p731_w548" font-name="ssexcelsior" bold="no" italic="yes" font-size="8" font-color="#000000" rotation="0" angle="0" x="260.81" y="82.254" base="87.95" width="30.7829" height="7.552">squirting</TOKEN>
<TOKEN sid="p731_s804085" id="p731_w549" font-name="ssexcelsior" bold="no" italic="yes" font-size="8" font-color="#000000" rotation="0" angle="0" x="293.592" y="82.254" base="87.95" width="30.3826" height="7.552">windows</TOKEN>
<TOKEN sid="p731_s804086" id="p731_w550" font-name="ssexcelsior" bold="no" italic="yes" font-size="8" font-color="#000000" rotation="0" angle="0" x="325.973" y="82.254" base="87.95" width="15.5909" height="7.552">with</TOKEN>
<TOKEN sid="p731_s804087" id="p731_w551" font-name="ssexcelsior" bold="no" italic="yes" font-size="8" font-color="#000000" rotation="0" angle="0" x="343.562" y="82.254" base="87.95" width="20.484" height="7.552">water.</TOKEN>
</quote>
</seg>
</sense>
</entry>
