<entry xml:lang="en">
<form type="lemma">
<orth>
<TOKEN sid="p27_s28508" id="p27_w73" font-name="ssexcelsior" symbolic="yes" fixed-width="yes" bold="no" italic="yes" font-size="8" font-color="#000000" rotation="0" angle="0" x="109.142" y="137.344" base="143.04" width="35.5975" height="7.552">benefactor</TOKEN>
</orth>
<form type="variant">
<pron>
<TOKEN sid="p27_s28509" id="p27_w74" font-name="ssexcelsior" symbolic="yes" fixed-width="yes" bold="no" italic="yes" font-size="8" font-color="#000000" rotation="0" angle="0" x="147.72" y="137.344" base="143.04" width="14.3986" height="7.552">who</TOKEN>
</pron>
</form>
<form type="inflected">
<TOKEN sid="p27_s28510" id="p27_w75" font-name="ssexcelsior" symbolic="yes" fixed-width="yes" bold="no" italic="yes" font-size="8" font-color="#000000" rotation="0" angle="0" x="165.099" y="137.344" base="143.04" width="26.383" height="7.552">insisted</TOKEN>
</form>
</form>
<sense>
<gramGrp>
<pos>
<TOKEN sid="p27_s28511" id="p27_w76" font-name="ssexcelsior" symbolic="yes" fixed-width="yes" bold="no" italic="yes" font-size="8" font-color="#000000" rotation="0" angle="0" x="194.462" y="137.344" base="143.04" width="8.40168" height="7.552">on</TOKEN>
<TOKEN sid="p27_s28512" id="p27_w77" font-name="ssexcelsior" symbolic="yes" fixed-width="yes" bold="no" italic="yes" font-size="8" font-color="#000000" rotation="0" angle="0" x="205.843" y="137.344" base="143.04" width="37.9663" height="7.552">anonymity.</TOKEN>
</pos>
</gramGrp>
<def xml:lang="sl">
<seg type="lemma">
<TOKEN sid="p27_s28514" id="p27_w79" font-name="ssexcelsior" symbolic="yes" serif="yes" bold="no" italic="no" font-size="5.5" font-color="#000000" rotation="0" angle="0" x="69.97" y="148.194" base="152.11" width="27.2171" height="5.192">UNCOUNT</TOKEN>
<TOKEN sid="p27_s28515" id="p27_w80" font-name="ssexcelsior" symbolic="yes" serif="yes" bold="no" italic="no" font-size="5.5" font-color="#000000" rotation="0" angle="0" x="99.1923" y="148.194" base="152.11" width="4.12335" height="5.192">N</TOKEN>
</seg>
<TOKEN sid="p27_s28516" id="p27_w81" font-name="ssexcelsior" symbolic="yes" serif="yes" bold="no" italic="no" font-size="5.5" font-color="#000000" rotation="0" angle="0" x="105.32" y="148.194" base="152.11" width="10.7197" height="5.192">with</TOKEN>
<TOKEN sid="p27_s28517" id="p27_w82" font-name="ssexcelsior" symbolic="yes" serif="yes" bold="no" italic="no" font-size="5.5" font-color="#000000" rotation="0" angle="0" x="118.045" y="148.194" base="152.11" width="14.0268" height="5.192">SUPP</TOKEN>
<TOKEN sid="p27_s28518" id="p27_w83" font-name="ssexcelsior" fixed-width="yes" bold="yes" italic="no" font-size="8" font-color="#000000" rotation="0" angle="0" x="134.96" y="146.414" base="152.11" width="12.8002" height="7.552">The</TOKEN>
<TOKEN sid="p27_s28519" id="p27_w84" font-name="ssexcelsior" fixed-width="yes" bold="yes" italic="no" font-size="8" font-color="#000000" rotation="0" angle="0" x="150.67" y="146.414" base="152.11" width="36.4046" height="7.552">anonymity</TOKEN>
<TOKEN sid="p27_s28520" id="p27_w85" font-name="ssexcelsior" fixed-width="yes" bold="yes" italic="no" font-size="8" font-color="#000000" rotation="0" angle="0" x="189.985" y="146.414" base="152.11" width="6.80328" height="7.552">of</TOKEN>
<TOKEN sid="p27_s28521" id="p27_w86" font-name="ssexcelsior" fixed-width="yes" bold="yes" italic="no" font-size="8" font-color="#000000" rotation="0" angle="0" x="199.699" y="146.414" base="152.11" width="35.195" height="7.552">something</TOKEN>
<TOKEN sid="p27_s28522" id="p27_w87" font-name="ssexcelsior" symbolic="yes" serif="yes" bold="no" italic="no" font-size="8" font-color="#000000" rotation="0" angle="0" x="237.81" y="146.414" base="152.11" width="6.00048" height="7.552">je</TOKEN>
</def>
<cit type="translationEquivalent">
<quote>
<TOKEN sid="p27_s28523" id="p27_w88" font-name="ssexcelsior" symbolic="yes" serif="yes" bold="no" italic="no" font-size="8" font-color="#000000" rotation="0" angle="0" x="62.3898" y="155.484" base="161.18" width="25.8329" height="7.552">dejstvo,</TOKEN>
</quote>
</cit>
</sense>
</entry>
