<entry xml:lang="en">
<form type="lemma">
<orth>
<TOKEN sid="p809_s891612" id="p809_w585" font-name="ssunivers" symbolic="yes" serif="yes" bold="yes" italic="no" font-size="9" font-color="#000000" rotation="0" angle="0" x="255.14" y="81.542" base="87.95" width="26.3203" height="8.514">trillion</TOKEN>
</orth>
<form type="variant">
<pron>
<TOKEN sid="p809_s891613" id="p809_w586" font-name="ssexcelsior" symbolic="yes" fixed-width="yes" bold="no" italic="no" font-size="7.25" font-color="#000000" rotation="0" angle="0" x="282.99" y="82.788" base="87.95" width="29.2716" height="6.844">/tr&#203;lj6n/.</TOKEN>
</pron>
</form>
</form>
<sense>
<def xml:lang="sl">
<seg type="lemma">
<TOKEN sid="p809_s891614" id="p809_w587" font-name="ssexcelsior" symbolic="yes" serif="yes" fixed-width="yes" bold="yes" italic="no" font-size="8" font-color="#000000" rotation="0" angle="0" x="313.82" y="82.254" base="87.95" width="5.6016" height="7.552">A</TOKEN>
<TOKEN sid="p809_s891615" id="p809_w588" font-name="ssexcelsior" symbolic="yes" serif="yes" fixed-width="yes" bold="yes" italic="no" font-size="8" font-color="#000000" rotation="0" angle="0" x="320.989" y="82.254" base="87.95" width="23.6981" height="7.552">trillion</TOKEN>
</seg>
<TOKEN sid="p809_s891616" id="p809_w589" font-name="ssexcelsior" symbolic="yes" fixed-width="yes" bold="no" italic="no" font-size="8" font-color="#000000" rotation="0" angle="0" x="346.279" y="82.254" base="87.95" width="5.95584" height="7.552">je</TOKEN>
<TOKEN sid="p809_s891617" id="p809_w590" font-name="ssexcelsior" symbolic="yes" fixed-width="yes" bold="no" italic="no" font-size="8" font-color="#000000" rotation="0" angle="0" x="353.793" y="82.254" base="87.95" width="24.143" height="7.552">milijon</TOKEN>
<TOKEN sid="p809_s891618" id="p809_w591" font-name="ssexcelsior" symbolic="yes" fixed-width="yes" bold="no" italic="no" font-size="8" font-color="#000000" rotation="0" angle="0" x="379.494" y="82.254" base="87.95" width="33.187" height="7.552">milijonov.</TOKEN>
</def>
<cit type="translationEquivalent">
<quote>
<TOKEN sid="p809_s891620" id="p809_w593" font-name="ssexcelsior" symbolic="yes" fixed-width="yes" bold="no" italic="no" font-size="8" font-color="#000000" rotation="0" angle="0" x="420.07" y="82.254" base="87.95" width="22.1414" height="7.552">bilijon</TOKEN>
</quote>
</cit>
</sense>
</entry>
